patent_stil/__init__.py
patent_stil/fpo_patent.py
patent_stil/google_patent.py
patent_stil/utils.py
patent_stil-0.1.2.dist-info/LICENSE
patent_stil-0.1.2.dist-info/METADATA
patent_stil-0.1.2.dist-info/WHEEL
patent_stil-0.1.2.dist-info/RECORD
